metalogos/__init__.py
metalogos/aesthetics.py
metalogos/entropy.py
metalogos/ethics.py
metalogos/mind.py
metalogos/semantics.py
metalogos-0.1.0.dist-info/licenses/LICENSE
metalogos-0.1.0.dist-info/METADATA
metalogos-0.1.0.dist-info/WHEEL
metalogos-0.1.0.dist-info/top_level.txt
metalogos-0.1.0.dist-info/RECORD
