Metadata-Version: 2.4
Name: metalogos
Version: 0.1.0
Summary: A reflective Python library where logic meets longing — blending AI, philosophy, and aesthetics.
Home-page: https://github.com/ashar0800/metalogos
Author: Ashar Nasir
Author-email: asharnasir0800@example.com
Classifier: Development Status :: 3 - Alpha
Classifier: Intended Audience :: Science/Research
Classifier: License :: OSI Approved :: MIT License
Classifier: Programming Language :: Python :: 3
Classifier: Topic :: Scientific/Engineering :: Artificial Intelligence
Requires-Python: >=3.8
License-File: LICENSE
Dynamic: author
Dynamic: author-email
Dynamic: classifier
Dynamic: description
Dynamic: description-content-type
Dynamic: home-page
Dynamic: license-file
Dynamic: requires-python
Dynamic: summary
